[
  {
    "id": 4,
    "userId": null,
    "avatarUrl": "https://images.unsplash.com/photo-1545996124-2e6a2a4f4c63?w=200&h=200&fit=crop&u=Auto%20Helper",
    "name": "Auto Helper",
    "specialty": null,
    "bio": null,
    "crp": null,
    "active": true,
    "registrationStatus": "PENDING",
    "createdAt": "2025-10-08T23:43:20.389Z",
    "updatedAt": "2025-10-14T18:48:20.573Z"
  },
  {
    "id": 9,
    "userId": null,
    "avatarUrl": "https://images.unsplash.com/photo-1524504388940-b1c1722653e1?w=200&h=200&fit=crop&u=Dra.%20Ana",
    "name": "Dra. Ana",
    "specialty": "Psicologia",
    "bio": null,
    "crp": null,
    "active": true,
    "registrationStatus": "PENDING",
    "createdAt": "2025-10-09T03:07:01.823Z",
    "updatedAt": "2025-10-14T18:48:20.579Z"
  },
  {
    "id": 10,
    "userId": null,
    "avatarUrl": "https://images.unsplash.com/photo-1524504388940-b1c1722653e1?w=200&h=200&fit=crop&u=Admin",
    "name": "Admin",
    "specialty": null,
    "bio": null,
    "crp": null,
    "active": true,
    "registrationStatus": "PENDING",
    "createdAt": "2025-10-09T16:57:14.898Z",
    "updatedAt": "2025-10-14T18:48:20.621Z"
  },
  {
    "id": 8,
    "userId": null,
    "avatarUrl": "https://images.unsplash.com/photo-1524504388940-9a1f0a1f3c4b?w=200&h=200&fit=crop&u=Ana",
    "name": "Ana",
    "specialty": null,
    "bio": null,
    "crp": null,
    "active": true,
    "registrationStatus": "PENDING",
    "createdAt": "2025-10-09T03:00:11.736Z",
    "updatedAt": "2025-10-14T18:48:20.628Z"
  },
  {
    "id": 12,
    "userId": null,
    "avatarUrl": "https://images.unsplash.com/photo-1524504388940-b1c1722653e1?w=200&h=200&fit=crop&u=Dra.%20Ana",
    "name": "Dra. Ana",
    "specialty": "Psicologia",
    "bio": null,
    "crp": null,
    "active": true,
    "registrationStatus": "PENDING",
    "createdAt": "2025-10-14T17:52:35.639Z",
    "updatedAt": "2025-10-14T18:48:20.634Z"
  },
  {
    "id": 16,
    "userId": 30,
    "avatarUrl": "https://images.unsplash.com/photo-1524504388940-b1c1722653e1?w=200&h=200&fit=crop&u=Jo%C3%A3o%20Santos",
    "name": "João Santos",
    "specialty": "Psiquiatria",
    "bio": "Psiquiatra com experiência em gestão de transtornos do humor e uso racional de psicofármacos. Atendimento baseado em protocolos clínicos.",
    "crp": null,
    "active": true,
    "registrationStatus": "PENDING",
    "createdAt": "2025-10-14T17:52:36.355Z",
    "updatedAt": "2025-10-14T18:48:20.639Z"
  },
  {
    "id": 11,
    "userId": 1,
    "avatarUrl": "https://images.unsplash.com/photo-1546967191-fdfb13ed6b1b?w=200&h=200&fit=crop",
    "name": "Fernanda",
    "specialty": null,
    "bio": null,
    "crp": null,
    "active": true,
    "registrationStatus": "PENDING",
    "createdAt": "2025-10-09T16:57:32.996Z",
    "updatedAt": "2025-10-14T18:48:20.431Z"
  },
  {
    "id": 7,
    "userId": null,
    "avatarUrl": "https://images.unsplash.com/photo-1531123414780-f8f5e0e5d0bb?w=200&h=200&fit=crop",
    "name": "Dr João",
    "specialty": null,
    "bio": null,
    "crp": null,
    "active": true,
    "registrationStatus": "PENDING",
    "createdAt": "2025-10-08T23:45:03.63Z",
    "updatedAt": "2025-10-14T18:48:20.49Z"
  },
  {
    "id": 5,
    "userId": null,
    "avatarUrl": "https://images.unsplash.com/photo-1524504388940-9a1f0a1f3c4b?w=200&h=200&fit=crop&u=Helper",
    "name": "Helper",
    "specialty": null,
    "bio": null,
    "crp": null,
    "active": true,
    "registrationStatus": "PENDING",
    "createdAt": "2025-10-08T23:45:03.597Z",
    "updatedAt": "2025-10-14T18:48:20.495Z"
  },
  {
    "id": 1,
    "userId": null,
    "avatarUrl": "https://images.unsplash.com/photo-1524504388940-b1c1722653e1?w=200&h=200&fit=crop&u=Dra.%20Ana",
    "name": "Dra. Ana",
    "specialty": "Psicologia",
    "bio": null,
    "crp": null,
    "active": true,
    "registrationStatus": "PENDING",
    "createdAt": "2025-10-08T18:31:11.257Z",
    "updatedAt": "2025-10-14T18:48:20.515Z"
  },
  {
    "id": 2,
    "userId": null,
    "avatarUrl": "https://images.unsplash.com/photo-1524504388940-b1c1722653e1?w=200&h=200&fit=crop&u=Dra.%20Ana",
    "name": "Dra. Ana",
    "specialty": "Psicologia",
    "bio": null,
    "crp": null,
    "active": true,
    "registrationStatus": "PENDING",
    "createdAt": "2025-10-08T19:01:45.975Z",
    "updatedAt": "2025-10-14T18:48:20.522Z"
  },
  {
    "id": 3,
    "userId": null,
    "avatarUrl": "https://images.unsplash.com/photo-1524504388940-b1c1722653e1?w=200&h=200&fit=crop&u=Dra.%20Ana",
    "name": "Dra. Ana",
    "specialty": "Psicologia",
    "bio": null,
    "crp": null,
    "active": true,
    "registrationStatus": "PENDING",
    "createdAt": "2025-10-08T19:09:03.306Z",
    "updatedAt": "2025-10-14T18:48:20.531Z"
  },
  {
    "id": 6,
    "userId": null,
    "avatarUrl": "https://images.unsplash.com/photo-1545996124-2e6a2a4f4c63?w=200&h=200&fit=crop&u=Dra%20Ana%20",
    "name": "Dra Ana ",
    "specialty": null,
    "bio": null,
    "crp": null,
    "active": true,
    "registrationStatus": "PENDING",
    "createdAt": "2025-10-08T23:45:03.623Z",
    "updatedAt": "2025-10-14T18:48:20.537Z"
  },
  {
    "id": 13,
    "userId": 27,
    "avatarUrl": "https://images.unsplash.com/photo-1544005313-94ddf0286df2?w=200&h=200&fit=crop&u=Dra.%20Ana%20Silva",
    "name": "Dra. Ana Silva",
    "specialty": "Psicologia Clínica",
    "bio": "Psicóloga com 10 anos de experiência em terapia cognitivo-comportamental, com foco em ansiedade e depressão. Atendimento acolhedor e orientado a evidências.",
    "crp": null,
    "active": true,
    "registrationStatus": "PENDING",
    "createdAt": "2025-10-14T17:52:35.801Z",
    "updatedAt": "2025-10-14T18:48:20.544Z"
  }
]
